yodas/__init__.py
yodas/menuClass.py
yodas/yodaClass.py
yodas/utilities/__init__.py
yodas/utilities/strings.py
yodas/utilities/utilities.py
yodas-1.4.1.dist-info/LICENSE
yodas-1.4.1.dist-info/METADATA
yodas-1.4.1.dist-info/WHEEL
yodas-1.4.1.dist-info/top_level.txt
yodas-1.4.1.dist-info/RECORD
