Metadata-Version: 2.1
Name: yodas
Version: 1.4.1
Summary: A set of helpful classes for a CLI interface
Home-page: https://github.com/veryheavypickle/yodaTools
Author: Yoda
Author-email: dev-yoda@proton.me
Project-URL: Github, https://github.com/veryheavypickle/yodaTools
Classifier: Programming Language :: Python :: 3
Classifier: License :: OSI Approved :: GNU General Public License v3 (GPLv3)
Classifier: Operating System :: OS Independent
Requires-Python: >=3.6
License-File: LICENSE
